{"title":"Linux搭建Qt5.14开发环境-傻瓜式","slug":"qt-linux-lazy","date":"2020-06-29T12:25:52.000Z","updated":"2020-06-29T13:19:13.760Z","comments":true,"path":"api/articles/qt-linux-lazy.json","excerpt":null,"covers":["/2020/06/29/qt-linux-lazy/linux_qt1.jpg","/2020/06/29/qt-linux-lazy/linux_qt2.jpg","/2020/06/29/qt-linux-lazy/linux_qt3.jpg","/2020/06/29/qt-linux-lazy/linux_qt4.jpg","/2020/06/29/qt-linux-lazy/linux_qt5.jpg","/2020/06/29/qt-linux-lazy/linux_qt6.jpg","/2020/06/29/qt-linux-lazy/linux_qt7.jpg","/2020/06/29/qt-linux-lazy/linux_qt8.jpg","/2020/06/29/qt-linux-lazy/linux_qt9.jpg","/2020/06/29/qt-linux-lazy/linux_qt10.jpg","/2020/06/29/qt-linux-lazy/linux_qt11.jpg","/2020/06/29/qt-linux-lazy/linux_qt12.jpg","/2020/06/29/qt-linux-lazy/linux_qt13.jpg","/2020/06/29/qt-linux-lazy/linux_qt14.jpg","/2020/06/29/qt-linux-lazy/linux_qt15.jpg","/2020/06/29/qt-linux-lazy/linux_qt16.jpg","/2020/06/29/qt-linux-lazy/linux_qt17.jpg","/2020/06/29/qt-linux-lazy/linux_qt18.jpg","/2020/06/29/qt-linux-lazy/linux_qt19.jpg","/2020/06/29/qt-linux-lazy/linux_qt20.jpg","/2020/06/29/qt-linux-lazy/linux_qt21.jpg","/2020/06/29/qt-linux-lazy/linux_qt22.jpg","/2020/06/29/qt-linux-lazy/linux_qt23.jpg","/2020/06/29/qt-linux-lazy/linux_qt24.jpg","/2020/06/29/qt-linux-lazy/linux_qt25.jpg","/2020/06/29/qt-linux-lazy/linux_qt26.jpg"],"content":"<h1 id=\"0-安装c-开发环境\"><a href=\"#0-安装c-开发环境\" class=\"headerlink\" title=\"0 安装c++开发环境\"></a>0 安装c++开发环境</h1><p>一般的系统应该都默认装了=。=</p>\n<pre class=\" language-shell\"><code class=\"language-shell\">sudo apt-get update\nsudo apt-get install gcc g++ </code></pre>\n<h1 id=\"1\"><a href=\"#1\" class=\"headerlink\" title=\"1\"></a>1</h1><p>输入网址 <a href=\"http://download.qt.io/archive/qt/5.14/5.14.0/\" target=\"_blank\" rel=\"noopener\">http://download.qt.io/archive/qt/5.14/5.14.0/</a> </p>\n<blockquote>\n<p>上面的网站，估计下载很慢，这里贴上一个清华源的。<a href=\"https://mirrors.tuna.tsinghua.edu.cn/qt/official_releases/qt/5.14/5.14.0/\" target=\"_blank\" rel=\"noopener\">https://mirrors.tuna.tsinghua.edu.cn/qt/official_releases/qt/5.14/5.14.0/</a></p>\n</blockquote>\n<p>下载run文件，这是Linux上的一个可执行文件的格式</p>\n<p><img src=\"/2020/06/29/qt-linux-lazy/linux_qt1.jpg\" alt></p>\n<h1 id=\"2\"><a href=\"#2\" class=\"headerlink\" title=\"2\"></a>2</h1><p>下载完成，进入下载目录，右键-终端。执行命令，给可执行权限</p>\n<pre class=\" language-shell\"><code class=\"language-shell\">chmod a+x ./qt-opensource-linux-x64-5.14.0.run</code></pre>\n<p>然后终端运行，开始安装</p>\n<pre class=\" language-shell\"><code class=\"language-shell\">./qt-opensource-linux-x64-5.14.0.run</code></pre>\n<p><img src=\"/2020/06/29/qt-linux-lazy/linux_qt2.jpg\" alt> </p>\n<p>一直下一步 or next，自己选择安装目录（这个不讲究，随便一个就行，我这里选择默认的</p>\n<p><img src=\"/2020/06/29/qt-linux-lazy/linux_qt3.jpg\" alt> </p>\n<p>next</p>\n<hr>\n<p><img src=\"/2020/06/29/qt-linux-lazy/linux_qt4.jpg\" alt> </p>\n<p>红框中的两个是必选的，然后我一个个解释</p>\n<ul>\n<li>Desktop gcc 64-bit 这是Qt预编译好的64位的Qt库。</li>\n<li>Developer and Designer Tools 这就是我们的主角QtCreator</li>\n<li>Qt WebEngine 这是Qt替代Webkit的库，这个装不装都行。</li>\n</ul>\n<hr>\n<p>接下来就同意人家协议呗，不同意不给用。选LGPL（这个动态链接不花钱</p>\n<p><img src=\"/2020/06/29/qt-linux-lazy/linux_qt5.jpg\" alt> </p>\n<hr>\n<p>安装呗</p>\n<p><img src=\"/2020/06/29/qt-linux-lazy/linux_qt6.jpg\" alt> </p>\n<hr>\n<p>挺快的</p>\n<p><img src=\"/2020/06/29/qt-linux-lazy/linux_qt7.jpg\" alt> </p>\n<hr>\n<p>点击完成，打开QtCreator </p>\n<p><img src=\"/2020/06/29/qt-linux-lazy/linux_qt8.jpg\" alt> </p>\n<p>点击工具菜单下的选项，打开</p>\n<p><img src=\"/2020/06/29/qt-linux-lazy/linux_qt9.jpg\" alt> </p>\n<p>观察Kit的选择，发现Qt的版本已经安装好了，对应的路径也在上面（装上就是配置好的</p>\n<p><img src=\"/2020/06/29/qt-linux-lazy/linux_qt10.jpg\" alt> </p>\n<p>点开编译器 发现系统自带的GCC也已经识别出来了。（我这里也是什么都没动</p>\n<p><img src=\"/2020/06/29/qt-linux-lazy/linux_qt11.jpg\" alt> </p>\n<p>然后点开Kit，发现编译器已经选好了，QtVersion也已经好了。（这里也什么都没动<br>这说明环境已经搭建好了。然后点击确定</p>\n<p><img src=\"/2020/06/29/qt-linux-lazy/linux_qt12.jpg\" alt> </p>\n<h1 id=\"测试\"><a href=\"#测试\" class=\"headerlink\" title=\"测试\"></a>测试</h1><h2 id=\"新建项目\"><a href=\"#新建项目\" class=\"headerlink\" title=\"新建项目\"></a>新建项目</h2><p>点击New按钮，然后跟着图一步步来</p>\n<h3 id=\"1-1\"><a href=\"#1-1\" class=\"headerlink\" title=\"1\"></a>1</h3><p><img src=\"/2020/06/29/qt-linux-lazy/linux_qt13.jpg\" alt> </p>\n<h3 id=\"2-1\"><a href=\"#2-1\" class=\"headerlink\" title=\"2\"></a>2</h3><p><img src=\"/2020/06/29/qt-linux-lazy/linux_qt14.jpg\" alt> </p>\n<h3 id=\"4\"><a href=\"#4\" class=\"headerlink\" title=\"4\"></a>4</h3><p><img src=\"/2020/06/29/qt-linux-lazy/linux_qt15.jpg\" alt> </p>\n<h3 id=\"5\"><a href=\"#5\" class=\"headerlink\" title=\"5\"></a>5</h3><p><img src=\"/2020/06/29/qt-linux-lazy/linux_qt16.jpg\" alt> </p>\n<h3 id=\"6\"><a href=\"#6\" class=\"headerlink\" title=\"6\"></a>6</h3><p><img src=\"/2020/06/29/qt-linux-lazy/linux_qt17.jpg\" alt> </p>\n<h3 id=\"7\"><a href=\"#7\" class=\"headerlink\" title=\"7\"></a>7</h3><p><img src=\"/2020/06/29/qt-linux-lazy/linux_qt18.jpg\" alt> </p>\n<h3 id=\"8\"><a href=\"#8\" class=\"headerlink\" title=\"8\"></a>8</h3><p>然后选咱们刚才配好的Kit（实际上啥都没干。<br><img src=\"/2020/06/29/qt-linux-lazy/linux_qt19.jpg\" alt> </p>\n<h3 id=\"9\"><a href=\"#9\" class=\"headerlink\" title=\"9\"></a>9</h3><p><img src=\"/2020/06/29/qt-linux-lazy/linux_qt20.jpg\" alt> </p>\n<p>点击完成<br>项目就建立好了。</p>\n<h2 id=\"编译\"><a href=\"#编译\" class=\"headerlink\" title=\"编译\"></a>编译</h2><h3 id=\"1-2\"><a href=\"#1-2\" class=\"headerlink\" title=\"1\"></a>1</h3><p>右键项目先 执行qmake -&gt; 构建</p>\n<p><img src=\"/2020/06/29/qt-linux-lazy/linux_qt21.jpg\" alt> </p>\n<h3 id=\"2-2\"><a href=\"#2-2\" class=\"headerlink\" title=\"2\"></a>2</h3><p>发现报错</p>\n<p><img src=\"/2020/06/29/qt-linux-lazy/linux_qt22.jpg\" alt> </p>\n<h3 id=\"3\"><a href=\"#3\" class=\"headerlink\" title=\"3\"></a>3</h3><p>缺少库而已。装上就行</p>\n<pre class=\" language-shell\"><code class=\"language-shell\">sudo apt-get install libgl1-mesa-dev libglu1-mesa-dev</code></pre>\n<p><img src=\"/2020/06/29/qt-linux-lazy/linux_qt23.jpg\" alt> </p>\n<h3 id=\"4-1\"><a href=\"#4-1\" class=\"headerlink\" title=\"4\"></a>4</h3><p>然后再构建<br>发现通过。</p>\n<p><img src=\"/2020/06/29/qt-linux-lazy/linux_qt24.jpg\" alt> </p>\n<h3 id=\"5-succeed\"><a href=\"#5-succeed\" class=\"headerlink\" title=\"5 succeed\"></a>5 succeed</h3><p>点击运行，发现运行成功！</p>\n<p><img src=\"/2020/06/29/qt-linux-lazy/linux_qt25.jpg\" alt> </p>\n<p><img src=\"/2020/06/29/qt-linux-lazy/linux_qt26.jpg\" alt> </p>\n<h1 id=\"小结\"><a href=\"#小结\" class=\"headerlink\" title=\"小结\"></a>小结</h1><p>至此，Linux上的Qt环境的搭建已经完成，这个是方式是相当简单的，基本上一直下一步就可以了。</p>\n","more":"<h1 id=\"0-安装c-开发环境\"><a href=\"#0-安装c-开发环境\" class=\"headerlink\" title=\"0 安装c++开发环境\"></a>0 安装c++开发环境</h1><p>一般的系统应该都默认装了=。=</p>\n<pre><code class=\"shell\">sudo apt-get update\nsudo apt-get install gcc g++ </code></pre>\n<h1 id=\"1\"><a href=\"#1\" class=\"headerlink\" title=\"1\"></a>1</h1><p>输入网址 <a href=\"http://download.qt.io/archive/qt/5.14/5.14.0/\" target=\"_blank\" rel=\"noopener\">http://download.qt.io/archive/qt/5.14/5.14.0/</a> </p>\n<blockquote>\n<p>上面的网站，估计下载很慢，这里贴上一个清华源的。<a href=\"https://mirrors.tuna.tsinghua.edu.cn/qt/official_releases/qt/5.14/5.14.0/\" target=\"_blank\" rel=\"noopener\">https://mirrors.tuna.tsinghua.edu.cn/qt/official_releases/qt/5.14/5.14.0/</a></p>\n</blockquote>\n<p>下载run文件，这是Linux上的一个可执行文件的格式</p>\n<p><img src=\"/2020/06/29/qt-linux-lazy/linux_qt1.jpg\" alt></p>\n<h1 id=\"2\"><a href=\"#2\" class=\"headerlink\" title=\"2\"></a>2</h1><p>下载完成，进入下载目录，右键-终端。执行命令，给可执行权限</p>\n<pre><code class=\"shell\">chmod a+x ./qt-opensource-linux-x64-5.14.0.run</code></pre>\n<p>然后终端运行，开始安装</p>\n<pre><code class=\"shell\">./qt-opensource-linux-x64-5.14.0.run</code></pre>\n<p><img src=\"/2020/06/29/qt-linux-lazy/linux_qt2.jpg\" alt> </p>\n<p>一直下一步 or next，自己选择安装目录（这个不讲究，随便一个就行，我这里选择默认的</p>\n<p><img src=\"/2020/06/29/qt-linux-lazy/linux_qt3.jpg\" alt> </p>\n<p>next</p>\n<hr>\n<p><img src=\"/2020/06/29/qt-linux-lazy/linux_qt4.jpg\" alt> </p>\n<p>红框中的两个是必选的，然后我一个个解释</p>\n<ul>\n<li>Desktop gcc 64-bit 这是Qt预编译好的64位的Qt库。</li>\n<li>Developer and Designer Tools 这就是我们的主角QtCreator</li>\n<li>Qt WebEngine 这是Qt替代Webkit的库，这个装不装都行。</li>\n</ul>\n<hr>\n<p>接下来就同意人家协议呗，不同意不给用。选LGPL（这个动态链接不花钱</p>\n<p><img src=\"/2020/06/29/qt-linux-lazy/linux_qt5.jpg\" alt> </p>\n<hr>\n<p>安装呗</p>\n<p><img src=\"/2020/06/29/qt-linux-lazy/linux_qt6.jpg\" alt> </p>\n<hr>\n<p>挺快的</p>\n<p><img src=\"/2020/06/29/qt-linux-lazy/linux_qt7.jpg\" alt> </p>\n<hr>\n<p>点击完成，打开QtCreator </p>\n<p><img src=\"/2020/06/29/qt-linux-lazy/linux_qt8.jpg\" alt> </p>\n<p>点击工具菜单下的选项，打开</p>\n<p><img src=\"/2020/06/29/qt-linux-lazy/linux_qt9.jpg\" alt> </p>\n<p>观察Kit的选择，发现Qt的版本已经安装好了，对应的路径也在上面（装上就是配置好的</p>\n<p><img src=\"/2020/06/29/qt-linux-lazy/linux_qt10.jpg\" alt> </p>\n<p>点开编译器 发现系统自带的GCC也已经识别出来了。（我这里也是什么都没动</p>\n<p><img src=\"/2020/06/29/qt-linux-lazy/linux_qt11.jpg\" alt> </p>\n<p>然后点开Kit，发现编译器已经选好了，QtVersion也已经好了。（这里也什么都没动<br>这说明环境已经搭建好了。然后点击确定</p>\n<p><img src=\"/2020/06/29/qt-linux-lazy/linux_qt12.jpg\" alt> </p>\n<h1 id=\"测试\"><a href=\"#测试\" class=\"headerlink\" title=\"测试\"></a>测试</h1><h2 id=\"新建项目\"><a href=\"#新建项目\" class=\"headerlink\" title=\"新建项目\"></a>新建项目</h2><p>点击New按钮，然后跟着图一步步来</p>\n<h3 id=\"1-1\"><a href=\"#1-1\" class=\"headerlink\" title=\"1\"></a>1</h3><p><img src=\"/2020/06/29/qt-linux-lazy/linux_qt13.jpg\" alt> </p>\n<h3 id=\"2-1\"><a href=\"#2-1\" class=\"headerlink\" title=\"2\"></a>2</h3><p><img src=\"/2020/06/29/qt-linux-lazy/linux_qt14.jpg\" alt> </p>\n<h3 id=\"4\"><a href=\"#4\" class=\"headerlink\" title=\"4\"></a>4</h3><p><img src=\"/2020/06/29/qt-linux-lazy/linux_qt15.jpg\" alt> </p>\n<h3 id=\"5\"><a href=\"#5\" class=\"headerlink\" title=\"5\"></a>5</h3><p><img src=\"/2020/06/29/qt-linux-lazy/linux_qt16.jpg\" alt> </p>\n<h3 id=\"6\"><a href=\"#6\" class=\"headerlink\" title=\"6\"></a>6</h3><p><img src=\"/2020/06/29/qt-linux-lazy/linux_qt17.jpg\" alt> </p>\n<h3 id=\"7\"><a href=\"#7\" class=\"headerlink\" title=\"7\"></a>7</h3><p><img src=\"/2020/06/29/qt-linux-lazy/linux_qt18.jpg\" alt> </p>\n<h3 id=\"8\"><a href=\"#8\" class=\"headerlink\" title=\"8\"></a>8</h3><p>然后选咱们刚才配好的Kit（实际上啥都没干。<br><img src=\"/2020/06/29/qt-linux-lazy/linux_qt19.jpg\" alt> </p>\n<h3 id=\"9\"><a href=\"#9\" class=\"headerlink\" title=\"9\"></a>9</h3><p><img src=\"/2020/06/29/qt-linux-lazy/linux_qt20.jpg\" alt> </p>\n<p>点击完成<br>项目就建立好了。</p>\n<h2 id=\"编译\"><a href=\"#编译\" class=\"headerlink\" title=\"编译\"></a>编译</h2><h3 id=\"1-2\"><a href=\"#1-2\" class=\"headerlink\" title=\"1\"></a>1</h3><p>右键项目先 执行qmake -&gt; 构建</p>\n<p><img src=\"/2020/06/29/qt-linux-lazy/linux_qt21.jpg\" alt> </p>\n<h3 id=\"2-2\"><a href=\"#2-2\" class=\"headerlink\" title=\"2\"></a>2</h3><p>发现报错</p>\n<p><img src=\"/2020/06/29/qt-linux-lazy/linux_qt22.jpg\" alt> </p>\n<h3 id=\"3\"><a href=\"#3\" class=\"headerlink\" title=\"3\"></a>3</h3><p>缺少库而已。装上就行</p>\n<pre><code class=\"shell\">sudo apt-get install libgl1-mesa-dev libglu1-mesa-dev</code></pre>\n<p><img src=\"/2020/06/29/qt-linux-lazy/linux_qt23.jpg\" alt> </p>\n<h3 id=\"4-1\"><a href=\"#4-1\" class=\"headerlink\" title=\"4\"></a>4</h3><p>然后再构建<br>发现通过。</p>\n<p><img src=\"/2020/06/29/qt-linux-lazy/linux_qt24.jpg\" alt> </p>\n<h3 id=\"5-succeed\"><a href=\"#5-succeed\" class=\"headerlink\" title=\"5 succeed\"></a>5 succeed</h3><p>点击运行，发现运行成功！</p>\n<p><img src=\"/2020/06/29/qt-linux-lazy/linux_qt25.jpg\" alt> </p>\n<p><img src=\"/2020/06/29/qt-linux-lazy/linux_qt26.jpg\" alt> </p>\n<h1 id=\"小结\"><a href=\"#小结\" class=\"headerlink\" title=\"小结\"></a>小结</h1><p>至此，Linux上的Qt环境的搭建已经完成，这个是方式是相当简单的，基本上一直下一步就可以了。</p>\n","categories":[{"name":"Qt","path":"api/categories/Qt.json"},{"name":"Qt基础教程","path":"api/categories/Qt基础教程.json"}],"tags":[{"name":"Qt","path":"api/tags/Qt.json"}]}